S3Lister/__init__.py
S3Lister-1.0.0.dist-info/METADATA
S3Lister-1.0.0.dist-info/WHEEL
S3Lister-1.0.0.dist-info/top_level.txt
S3Lister-1.0.0.dist-info/RECORD
