Metadata-Version: 2.1
Name: S3Lister
Version: 1.0.0
Summary: A S3 listing test
Home-page: https://github.com/cybenari
Author: Cybenari
Author-email: idan@cybenari.com
Classifier: Programming Language :: Python :: 3
Classifier: License :: OSI Approved :: MIT License
Classifier: Operating System :: OS Independent
Requires-Python: >=3.6
